docs_proxy.py
pypi_docs_proxy-1.4.dist-info/DESCRIPTION.rst
pypi_docs_proxy-1.4.dist-info/METADATA
pypi_docs_proxy-1.4.dist-info/metadata.json
pypi_docs_proxy-1.4.dist-info/RECORD
pypi_docs_proxy-1.4.dist-info/top_level.txt
pypi_docs_proxy-1.4.dist-info/WHEEL
