Metadata-Version: 2.0
Name: pypi-docs-proxy
Version: 1.4
Summary: A Proxy for PyPI's Hosted Documentation
Home-page: UNKNOWN
Author: UNKNOWN
Author-email: UNKNOWN
License: UNKNOWN
Platform: UNKNOWN
Requires-Dist: boto
Requires-Dist: pyramid
Requires-Dist: tomb-routes
Requires-Dist: gunicorn
